{"level":"info","message":"Invoice deleted: {\"id\":\"6409b781dcf44e16472d2b17\"}"}
{"level":"info","message":"Invoice moved to delete: {\"client\":{\"address\":{\"address1\":\"address 1\",\"address2\":\"address 2\",\"city\":\"Jaipur\",\"state\":\"Rajasthan\",\"country\":\"India\",\"pinCode\":30303},\"firstName\":\"client first \",\"lastName\":\"client last\",\"email\":\"test@gmail.com\",\"phone\":1234567899,\"taxId\":\"rtyui098765456\"},\"firm\":{\"address\":{\"address1\":\"address 1\",\"address2\":\"address 2\",\"city\":\"Jaipur\",\"state\":\"Rajasthan\",\"country\":\"India\",\"pinCode\":303030},\"name\":\"firm\",\"phone\":1234567899,\"taxId\":\"FGHJK5678\",\"email\":\"firm@gmail.com\"},\"_id\":\"642d23548d336469d8c34126\",\"items\":[{\"itemName\":\"item 1\",\"unitPrice\":\"12\",\"quantity\":\"12\",\"amount\":0,\"desc\":\"item 1 desc\",\"_id\":\"642d23548d336469d8c34127\"}],\"tax\":[],\"subTotal\":144,\"total\":144,\"invoiceDate\":\"2023-04-05T00:00:00.000Z\",\"dueDate\":\"2023-04-19T00:00:00.000Z\",\"status\":\"Pending\",\"amountPaid\":0,\"dueAmount\":0,\"invoiceNumber\":68,\"termsNcondition\":[],\"currency\":\"₹\",\"partialPay\":true,\"draft\":false,\"orgId\":\"6399985b7e92ec25ec445190\",\"payment\":[],\"__v\":0,\"delete\":true}"}
